{"BackupList":[{"_indSOData":"%YAML 1.1\r\n%TAG !u! tag:unity3d.com,2011:\r\n--- !u!114 &11400000\r\nMonoBehaviour:\r\n  m_ObjectHideFlags: 0\r\n  m_CorrespondingSourceObject: {fileID: 0}\r\n  m_PrefabInstance: {fileID: 0}\r\n  m_PrefabAsset: {fileID: 0}\r\n  m_GameObject: {fileID: 0}\r\n  m_Enabled: 1\r\n  m_EditorHideFlags: 0\r\n  m_Script: {fileID: 11500000, guid: 2ef0956a4e729b84a8b9f3ea2feefbb5, type: 3}\r\n  m_Name: Element_New SO_Data_Key Characteristic Float 3 (Bust)-40002\r\n  m_EditorClassIdentifier: \r\n  _nameElement: Element_New SO_Data_Key Characteristic Float 3 (Bust)-40002\r\n  _identifier: \"\\u0414\\u0430\\u043B\\u044C\\u043D\\u043E\\u0441\\u0442\\u044C \\u043F\\u0440\\u044B\\u0436\\u043A\\u0430\"\r\n","_meta":"fileFormatVersion: 2\r\nguid: 7585cbf5335b9734a857c4543e49c91f\r\nNativeFormatImporter:\r\n  externalObjects: {}\r\n  mainObjectFileID: 11400000\r\n  userData: \r\n  assetBundleName: \r\n  assetBundleVariant: \r\n","Data":"{\"_key\":\"Дальность прыжка\"}"}]}